intake_dcat/__init__.py
intake_dcat/_version.py
intake_dcat/catalog.py
intake_dcat/cli.py
intake_dcat/distributions.py
intake_dcat/util.py
intake_dcat-0.4.0.dist-info/LICENSE
intake_dcat-0.4.0.dist-info/METADATA
intake_dcat-0.4.0.dist-info/WHEEL
intake_dcat-0.4.0.dist-info/entry_points.txt
intake_dcat-0.4.0.dist-info/top_level.txt
intake_dcat-0.4.0.dist-info/RECORD
