Metadata-Version: 2.1
Name: intake-dcat
Version: 0.4.0
Summary: DCAT to Intake Catalog translation layer
Home-page: https://github.com/CityOfLosAngeles/intake-dcat
Maintainer: Ian Rose
Maintainer-email: ian.rose@lacity.org
License: Apache-2.0 license
Keywords: intake dcat
Platform: UNKNOWN
Requires-Dist: geopandas (>=0.5)
Requires-Dist: intake (>=0.5)
Requires-Dist: intake-geopandas (>=0.2.2)
Requires-Dist: pyyaml
Requires-Dist: requests
Requires-Dist: s3fs
